h_tool_library/__init__.py
h_tool_library/__version__.py
h_tool_library/tools/__init__.py
h_tool_library/tools/base.py
h_tool_library/tools/email.py
h_tool_library/tools/hash.py
h_tool_library-0.0.5.dist-info/LICENSE
h_tool_library-0.0.5.dist-info/METADATA
h_tool_library-0.0.5.dist-info/WHEEL
h_tool_library-0.0.5.dist-info/top_level.txt
h_tool_library-0.0.5.dist-info/RECORD
